tests/__init__.py
tests/test_benchmark.py
vector_db_benchmark/__init__.py
vector_db_benchmark/benchmark.py
vector_db_benchmark-1.0.0.dist-info/LICENSE
vector_db_benchmark-1.0.0.dist-info/METADATA
vector_db_benchmark-1.0.0.dist-info/WHEEL
vector_db_benchmark-1.0.0.dist-info/top_level.txt
vector_db_benchmark-1.0.0.dist-info/RECORD
