Metadata-Version: 2.1
Name: vector_db_benchmark
Version: 1.0.0
Summary: Benchmarking tool for vector databases
Home-page: https://github.com/frozenparadox/vector_db_benchmark
Author: Sushant Lenka
Author-email: frostbitecryengine300@gmail.com
Keywords: vector database benchmark milvus numpy
Classifier: Programming Language :: Python :: 3
Classifier: License :: OSI Approved :: MIT License
Classifier: Operating System :: OS Independent
Requires-Python: >=3.6
License-File: LICENSE
Requires-Dist: numpy>=1.18.0
Requires-Dist: psutil>=5.7.0
Requires-Dist: matplotlib>=3.2.0
